abroca/__init__.py
abroca/compute_abroca.py
abroca/utils.py
abroca-0.1.3.dist-info/LICENSE
abroca-0.1.3.dist-info/METADATA
abroca-0.1.3.dist-info/WHEEL
abroca-0.1.3.dist-info/top_level.txt
abroca-0.1.3.dist-info/RECORD
