Metadata-Version: 2.1
Name: abroca
Version: 0.1.3
Summary: package for computing and visualizing the Absolute Between-ROC Area (ABROCA)
Home-page: https://github.com/VaibhavKaushik3220/abroca
Author: Disha, Vaibhav Kaushik
Author-email: disha.7003@gmail.com
License: UNKNOWN
Platform: UNKNOWN
Classifier: Programming Language :: Python :: 3
Classifier: License :: OSI Approved :: MIT License
Classifier: Operating System :: OS Independent
Requires-Python: >=3.6
